elegant_events/__init__.py
elegant_events-0.1.0.dist-info/METADATA
elegant_events-0.1.0.dist-info/WHEEL
elegant_events-0.1.0.dist-info/top_level.txt
elegant_events-0.1.0.dist-info/RECORD
