Metadata-Version: 2.1
Name: elegant-events
Version: 0.1.0
Summary: Easily send data and events between processes, or within a single process
Home-page: https://github.com/jeff-hykin/elegant_events
Author: Jeff Hykin
Author-email: jeff.hykin@gmail.com
License: MIT
Platform: UNKNOWN
Requires-Python: >=3.6
